MANIFEST.in
README.rst
doc.requirements.txt
requirements.txt
setup.cfg
setup.py
./fullmonty/__init__.py
./fullmonty/application_settings.py
./fullmonty/ashell.py
./fullmonty/backup.py
./fullmonty/capture_sys_output.py
./fullmonty/cd.py
./fullmonty/certs.py
./fullmonty/comparable_mixin.py
./fullmonty/find_directory.py
./fullmonty/fullmonty_app.py
./fullmonty/fullmonty_cli.py
./fullmonty/fullmonty_main.py
./fullmonty/fullmonty_settings.py
./fullmonty/graceful_interrupt_handler.py
./fullmonty/hack_sys_path.py
./fullmonty/indent.py
./fullmonty/list_helper.py
./fullmonty/local_shell.py
./fullmonty/make_bytes.py
./fullmonty/mangle.py
./fullmonty/mash.py
./fullmonty/md5.py
./fullmonty/method_missing_hook.py
./fullmonty/mkdir_p.py
./fullmonty/path.py
./fullmonty/prompt.py
./fullmonty/remote_shell.py
./fullmonty/safe_edit.py
./fullmonty/simple_logger.py
./fullmonty/split_all.py
./fullmonty/terminalsize.py
./fullmonty/timeit.py
./fullmonty/tmp_dir.py
./fullmonty/touch.py
./fullmonty/unionfs.py
./fullmonty/watchdog.py
FullMonty.egg-info/PKG-INFO
FullMonty.egg-info/SOURCES.txt
FullMonty.egg-info/dependency_links.txt
FullMonty.egg-info/entry_points.txt
FullMonty.egg-info/requires.txt
FullMonty.egg-info/top_level.txt
tests/test_backup.py
tests/test_comparable_mixin.py
tests/test_indent.py
tests/test_list_helper.py
tests/test_localshell.py
tests/test_make_bytes.py
tests/test_mangle.py
tests/test_mash.py
tests/test_method_missing_hook.py
tests/test_path.py
tests/test_remote_shell.py
tests/test_split_all.py
tests/test_tmp_dir.py