Metadata-Version: 1.1
Name: FullMonty
Version: 0.1.20
Summary: Eclectic library for applications.
Home-page: https://github.com/royw/fullmonty
Author: Roy Wright
Author-email: roy@wright.org
License: docs/license.rst
Platform: UNKNOWN
Classifier: Development Status :: 5 - Production/Stable
Classifier: Intended Audience :: Developers
Classifier: License :: OSI Approved :: MIT License
Classifier: Natural Language :: English
Classifier: Operating System :: OS Independent
Classifier: Programming Language :: Python :: 2.7
Classifier: Programming Language :: Python :: 3.5
Classifier: Programming Language :: Python :: 3.6
Classifier: Topic :: Software Development
